{"case_report_title":"Case Report - NamUs UP # 10925","case_status":"Unidentified","case_number":"2007-S-1310","date_found":"2007-07-21T07:00:00.000Z","date_created":"2013-01-14T20:41:00.000Z","date_last_modified":"2015-01-24T01:40:00.000Z","case_qa_reviewed_date":"2007-07-21T07:00:00.000Z","current_contact":{"agency":"Delaware Division of Forensic Science","phone":"302-577-3420"},"case_manager":{"name":"Patrick Quigley","phone":"302-933-3050"},"case_estimated_age":"Adult","case_minimum_age":"16 years","case_maximum_age":"50 years","case_race":"Black/African American","case_ethnicity":"","case_sex":"Male","case_weight":"\n\t\t\t\t\t,\n\t\t\t\t\tCannot Estimate\n\t\t\t\t","case_height":"\n\t\t\t\t\t,\n\t\t\t\t\tCannot Estimate\n\t\t\t\t","case_body_inventory_head_not_recovered":"checked","case_body_inventory_torso_not_recovered":"checked","case_body_inventory_limbs_not_recovered":"checked","case_body_condition":"Not recognizable - Partial skeletal parts only","case_minimum_year_of_death":"\n\t\t\t\t\t2000\n\t\t\t\t\tto\n\t\t\t\t\t2007\n\t\t\t\t","case_postmortem_interval":"\n\t\t\t\t\t\n\t\t\t\t\tYears\n\t\t\t\t","case_gps_coordinates":"","case_address_found_1":"150 yards off the west shoreline of Burton’s Island at Delaware Seashore State Park.","case_address_found_2":"","case_city_found":"Bottom Hills","case_state_found_id":"Delaware","case_zip_found":"","case_county_found_id":"Sussex","case_circumstances":"On 7/29/07 the Delaware Office of the Chief Medical Examiner was contacted by the Indian River Marina Office in reference to a human femur a fishermen had pulled up with his anchor at a depth of about 10 feet and about 150 yards off the west shoreline of Burton’s Island at Delaware Seashore State Park. (DNREC investigation document: Inlet 850, Rehoboth Beach, DE 19971, 5 miles S of DEWEY Beach Town Limits, Indian River Marina Boat Ramp.)","case_hair_color":"Unknown or Completely Bald","case_head_hair":"","case_body_hair":"","case_facial_hair":"","case_eye_color_left":"Unknown or Missing","case_eye_color_right":"Unknown or Missing","case_eye_description":"","fingerprints":"\n\t\t\t\t\t\n\t\t\t\t\t\tFingerprint information is currently not available\n\t\t\t\t\t\n\t\t\t\t","clothing_accessories":"","case_clothing_on_body":"","case_clothing_with_body":"","case_footwear":"","case_jewelry":"","case_eyewear":"","case_other_items_with_body":"","dental":"\n\t\t\t\t\t\n\t\t\t\t\t\tDental information / charting is currently not available\n\t\t\t\t\t\n\t\t\t\t","dna":"\n\t\t\t\t\t\n\t\t\t\t\t\tSample submitted - Tests complete\n\t\t\t\t\t\n\t\t\t\t","images":["/en/medias/thumb/17057"],"documents":"\n\t\t\t\t\n\t\t\t\t\t1 documents available for this case.\n\t\t\t\t\n\t\t\t"}