{"case_report_title":"Case Report - NamUs UP # 12917","case_status":"Unidentified","case_number":"ML12-01693","date_found":"2012-07-15T07:00:00.000Z","date_created":"2014-09-17T21:33:00.000Z","date_last_modified":"2015-02-10T04:50:00.000Z","case_qa_reviewed_date":"2012-07-15T07:00:00.000Z","current_contact":{"agency":"Pima Cnty Medical Examiners Ofc","phone":"520-724-8600"},"case_manager":{"name":"Bruce Anderson","phone":"520.724.8600"},"case_estimated_age":"Adult - Pre 60","case_minimum_age":"30 years","case_maximum_age":"55 years","case_race":"Other","case_ethnicity":"Hispanic/Latino","case_sex":"Male","case_weight":"\n\t\t\t\t\t150,\n\t\t\t\t\tEstimated\n\t\t\t\t","case_height":"\n\t\t\t\t\t64,\n\t\t\t\t\tMeasured\n\t\t\t\t","case_body_inventory_all_parts_recovered":"checked","case_body_condition":"Not recognizable - Mummified","case_minimum_year_of_death":"\n\t\t\t\t\t2012\n\t\t\t\t\tto\n\t\t\t\t\t2012\n\t\t\t\t","case_postmortem_interval":"\n\t\t\t\t\t\n\t\t\t\t\tWeeks\n\t\t\t\t","case_gps_coordinates":"N 32.40293 / W 112.84338","case_address_found_1":"1/4 mile east of Ajo Well Road","case_address_found_2":"","case_city_found":"near Ajo","case_state_found_id":"Arizona","case_zip_found":"","case_county_found_id":"Pima","case_circumstances":"Mummified remains found in remote desert area.  Fingerprints matched to USBP record, including multiple arrests and under several names, including Armando Lopez-Rivera.  None of the names are verified.  He was released from US prison in May 2012 and was deported to Mexico on 17 June 2012.  AAA","case_hair_color":"Gray or Partially Gray","case_head_hair":"black with some gray","case_body_hair":"","case_facial_hair":"","case_eye_color_left":"Brown","case_eye_color_right":"Brown","case_eye_description":"","fingerprints":"\n\t\t\t\t\t\n\t\t\t\t\t\tFingerprint information is available and entered\n\t\t\t\t\t\n\t\t\t\t","clothing_accessories":"","case_clothing_on_body":"dark jeans; brown belt with large silver buckle\n\nSee Images Page","case_clothing_with_body":"tan or white t-shirt; blue striped boxer shorts","case_footwear":"gray socks and brown shoes","case_jewelry":"","case_eyewear":"","case_other_items_with_body":"Dallas Cowboy's hat; toiletries; tan rope","dental":"\n\t\t\t\t\t\n\t\t\t\t\t\tDental information / charting is available and entered\n\t\t\t\t\t\n\t\t\t\t","dna":"\n\t\t\t\t\t\n\t\t\t\t\t\tSample available - Not yet submitted\n\t\t\t\t\t\n\t\t\t\t","images":["/en/medias/thumb/25478","/en/medias/thumb/25479","/en/medias/thumb/25480","/en/medias/thumb/25490"],"documents":"\n\t\t\t\t\n\t\t\t\t\tThere are currently no documents available for this case.<br><br><br><br>\n\t\t\t\t\n\t\t\t"}