{"case_report_title":"Case Report - NamUs UP # 13809","case_status":"Unidentified","case_number":"1981-1584","date_found":"1981-05-28T04:30:00.000Z","date_created":"2015-05-06T17:20:00.000Z","date_last_modified":"2016-09-07T14:53:00.000Z","case_qa_reviewed_date":"1981-05-28T04:30:00.000Z","current_contact":{"agency":"Miami-Dade Cnty Med Examiners Ofc","phone":"305-545-2425"},"case_manager":{"name":"Brittney McLaurin","phone":"305-545-2460"},"case_estimated_age":"Adult - Pre 60","case_minimum_age":"50 years","case_maximum_age":"60 years","case_race":"White","case_ethnicity":"","case_sex":"Male","case_weight":"\n\t\t\t\t\t125,\n\t\t\t\t\tMeasured\n\t\t\t\t","case_height":"\n\t\t\t\t\t68,\n\t\t\t\t\tMeasured\n\t\t\t\t","case_body_inventory_all_parts_recovered":"checked","case_body_condition":"Recognizable face","case_minimum_year_of_death":"\n\t\t\t\t\t1981\n\t\t\t\t\tto\n\t\t\t\t\t1981\n\t\t\t\t","case_postmortem_interval":"\n\t\t\t\t\t\n\t\t\t\t\t\n\t\t\t\t","case_gps_coordinates":"NW 32 Ave approx. 500 yrds North of NW 119 St","case_address_found_1":"","case_address_found_2":"","case_city_found":"Miami","case_state_found_id":"Florida","case_zip_found":"","case_county_found_id":"Miami-Dade","case_circumstances":"5/27/1981.","case_hair_color":"Black","case_head_hair":"Moderate length and with frontal balding.","case_body_hair":"","case_facial_hair":"","case_eye_color_left":"Brown","case_eye_color_right":"Brown","case_eye_description":"","case_scars_and_marks_details":"checked","fingerprints":"\n\t\t\t\t\t\n\t\t\t\t\t\tFingerprint information is available and entered\n\t\t\t\t\t\n\t\t\t\t","clothing_accessories":"","case_clothing_on_body":"Blue jeans,brown belt, black loafers, red and white socks, t-shirt and sleeveless undershirt, unknown color.","case_clothing_with_body":"Unknown","case_footwear":"Unknown","case_jewelry":"Unknown","case_eyewear":"Unknown","case_other_items_with_body":"","dental":"\n\t\t\t\t\t\n\t\t\t\t\t\tDental information / charting is available and entered\n\t\t\t\t\t\n\t\t\t\t","dna":"\n\t\t\t\t\t\n\t\t\t\t\t\tComplete - Insufficient DNA for profiling\n\t\t\t\t\t\n\t\t\t\t","images":["/en/medias/thumb/35505"],"documents":"\n\t\t\t\t\n\t\t\t\t\tThere are currently no documents available for this case.<br><br><br><br>\n\t\t\t\t\n\t\t\t"}