{"case_report_title":"Case Report - NamUs UP # 1388","case_status":"Unidentified","case_number":"96-04420","date_found":"1996-08-07T05:20:00.000Z","date_created":"2008-04-25T19:50:00.000Z","date_last_modified":"2014-08-10T20:27:00.000Z","case_qa_reviewed_date":"1996-08-07T05:20:00.000Z","current_contact":{"agency":"MD Ofc of Chief St Med Examiner","phone":"410-333-3225"},"case_manager":{"name":"Charlotte Noranbrock","phone":"410-333-3254"},"case_estimated_age":"Adult","case_minimum_age":"18 years","case_maximum_age":"60 years","case_race":"Black/African American","case_ethnicity":"","case_sex":"Female","case_weight":"\n\t\t\t\t\t179,\n\t\t\t\t\tEstimated\n\t\t\t\t","case_height":"\n\t\t\t\t\t,\n\t\t\t\t\tCannot Estimate\n\t\t\t\t","case_body_inventory_all_parts_recovered":"checked","case_body_condition":"Not recognizable - Traumatic injuries","case_minimum_year_of_death":"\n\t\t\t\t\t1996\n\t\t\t\t\tto\n\t\t\t\t\t1996\n\t\t\t\t","case_postmortem_interval":"\n\t\t\t\t\t\n\t\t\t\t\tMinutes\n\t\t\t\t","case_gps_coordinates":"","case_address_found_1":"3200 Block of Lohrs Lane","case_address_found_2":"","case_city_found":"Baltimore","case_state_found_id":"Maryland","case_zip_found":"21229","case_county_found_id":"Baltimore City","case_circumstances":"The subject was struck by a train","case_hair_color":"Brown","case_head_hair":"Brown","case_body_hair":"","case_facial_hair":"","case_eye_color_left":"Brown","case_eye_color_right":"Brown","case_eye_description":"","fingerprints":"\n\t\t\t\t\t\n\t\t\t\t\t\tFingerprint information is available elsewhere\n\t\t\t\t\t\n\t\t\t\t","clothing_accessories":"","case_clothing_on_body":"Green t-shirt, black bra, blue sweatpants and red panties","case_clothing_with_body":"","case_footwear":"Right brown shoe","case_jewelry":"","case_eyewear":"","case_other_items_with_body":"","dental":"\n\t\t\t\t\t\n\t\t\t\t\t\tDental information / charting is available and entered\n\t\t\t\t\t\n\t\t\t\t","dna":"\n\t\t\t\t\t\n\t\t\t\t\t\tSample is currently not available\n\t\t\t\t\t\n\t\t\t\t","images":["/en/medias/thumb/24853"],"documents":"\n\t\t\t\t\n\t\t\t\t\tThere are currently no documents available for this case.<br><br><br><br>\n\t\t\t\t\n\t\t\t"}