{"case_report_title":"Case Report - NamUs UP # 14795","case_status":"Unidentified","case_number":"01-19-634","date_found":"2001-10-15T07:00:00.000Z","date_created":"2016-02-18T17:30:00.000Z","date_last_modified":"2016-06-15T20:16:00.000Z","case_qa_reviewed_date":"2001-10-15T07:00:00.000Z","current_contact":{"agency":"Dist 19 Medical Examiners Ofc","phone":"772-464-7378"},"case_manager":{"name":"Kim Carroll","phone":"772-464-7378"},"case_estimated_age":"Adult","case_minimum_age":" years","case_maximum_age":" years","case_race":"Unsure","case_ethnicity":"","case_sex":"Unsure","case_weight":"\n\t\t\t\t\t,\n\t\t\t\t\tCannot Estimate\n\t\t\t\t","case_height":"\n\t\t\t\t\t,\n\t\t\t\t\tCannot Estimate\n\t\t\t\t","case_body_condition":"Not recognizable - Decomposing/putrefaction","case_minimum_year_of_death":"\n\t\t\t\t\t\n\t\t\t\t\tto\n\t\t\t\t\t\n\t\t\t\t","case_postmortem_interval":"\n\t\t\t\t\t\n\t\t\t\t\t\n\t\t\t\t","case_gps_coordinates":"","case_address_found_1":"Beach","case_address_found_2":"","case_city_found":"Fort Pierce","case_state_found_id":"Florida","case_zip_found":"","case_county_found_id":"St. Lucie","case_circumstances":"Severed finger of possible female found in a jar along beach in Fort Pierce, FL","case_hair_color":"","case_head_hair":"","case_body_hair":"","case_facial_hair":"","case_eye_color_left":"","case_eye_color_right":"","case_eye_description":"","fingerprints":"\n\t\t\t\t\t\n\t\t\t\t\t\tFingerprint information is currently not available\n\t\t\t\t\t\n\t\t\t\t","clothing_accessories":"","case_clothing_on_body":"","case_clothing_with_body":"","case_footwear":"","case_jewelry":"","case_eyewear":"","case_other_items_with_body":"","dental":"\n\t\t\t\t\t\n\t\t\t\t\t\tDental information / charting is currently not available\n\t\t\t\t\t\n\t\t\t\t","dna":"\n\t\t\t\t\t\n\t\t\t\t\t\tComplete - Insufficient DNA for profiling\n\t\t\t\t\t\n\t\t\t\t","images":[],"documents":"\n\t\t\t\t\n\t\t\t\t\tThere are currently no documents available for this case.<br><br><br><br>\n\t\t\t\t\n\t\t\t"}