{"case_report_title":"Case Report - NamUs UP # 15636","case_status":"Unidentified","case_number":"191583","date_found":"1984-12-16T20:56:00.000Z","date_created":"2016-08-19T19:49:00.000Z","date_last_modified":"2016-08-19T21:01:00.000Z","case_qa_reviewed_date":"1984-12-16T20:56:00.000Z","current_contact":{"agency":"Thomas Gilson","phone":"Cuyahoga Cnty Coroners Ofc"},"case_manager":{"name":"Anjanette Fischer","phone":"216-698-4267"},"case_estimated_age":"Adult - Pre 40","case_minimum_age":"30 years","case_maximum_age":"40 years","case_race":"Black/African American","case_ethnicity":"","case_sex":"Female","case_weight":"\n\t\t\t\t\t134,\n\t\t\t\t\tMeasured\n\t\t\t\t","case_height":"\n\t\t\t\t\t64,\n\t\t\t\t\tMeasured\n\t\t\t\t","case_body_inventory_all_parts_recovered":"checked","case_body_condition":"Not recognizable - Decomposing/putrefaction","case_minimum_year_of_death":"\n\t\t\t\t\t1984\n\t\t\t\t\tto\n\t\t\t\t\t1984\n\t\t\t\t","case_postmortem_interval":"\n\t\t\t\t\t2\n\t\t\t\t\tMonths\n\t\t\t\t","case_gps_coordinates":"","case_address_found_1":"On breakwall in Lake Erie","case_address_found_2":"12725 Lake Shore Blvd","case_city_found":"Bratenahl","case_state_found_id":"Ohio","case_zip_found":"44108","case_county_found_id":"Cuyahoga","case_circumstances":"Resident report seeing a body in the lake and called PD.","case_hair_color":"Black","case_head_hair":"","case_body_hair":"not mentioned in Autopsy report","case_facial_hair":"not mentioned in Autopsy report","case_eye_color_left":"Unknown or Missing","case_eye_color_right":"Unknown or Missing","case_eye_description":"Eyes missing due to decomposition","case_scars_and_marks_details":"checked","case_piercings_details":"checked","fingerprints":"\n\t\t\t\t\t\n\t\t\t\t\t\tFingerprint information is currently not available\n\t\t\t\t\t\n\t\t\t\t","clothing_accessories":"","case_clothing_on_body":"","case_clothing_with_body":"","case_footwear":"","case_jewelry":"","case_eyewear":"","case_other_items_with_body":"","dental":"\n\t\t\t\t\t\n\t\t\t\t\t\tDental information / charting is available and entered\n\t\t\t\t\t\n\t\t\t\t","dna":"\n\t\t\t\t\t\n\t\t\t\t\t\tSample is currently not available\n\t\t\t\t\t\n\t\t\t\t","images":[],"documents":"\n\t\t\t\t\n\t\t\t\t\tThere are currently no documents available for this case.<br><br><br><br>\n\t\t\t\t\n\t\t\t"}