{"case_report_title":"Case Report - NamUs UP # 15660","case_status":"Unidentified","case_number":"16-1366","date_found":"2016-07-12T07:00:00.000Z","date_created":"2016-08-24T22:09:00.000Z","date_last_modified":"2016-08-24T22:25:00.000Z","case_qa_reviewed_date":"2016-07-12T07:00:00.000Z","current_contact":{"agency":"Ofc Of The Kenedy Cnty JP","phone":"361-294-5787"},"case_manager":{"name":"Michael Nance","phone":"9185270080"},"case_estimated_age":"Adult - Pre 60","case_minimum_age":" years","case_maximum_age":" years","case_race":"White","case_ethnicity":"","case_sex":"Male","case_weight":"\n\t\t\t\t\t,\n\t\t\t\t\tCannot Estimate\n\t\t\t\t","case_height":"\n\t\t\t\t\t,\n\t\t\t\t\tCannot Estimate\n\t\t\t\t","case_body_condition":"Not recognizable - Decomposing/putrefaction","case_minimum_year_of_death":"\n\t\t\t\t\t\n\t\t\t\t\tto\n\t\t\t\t\t\n\t\t\t\t","case_postmortem_interval":"\n\t\t\t\t\t\n\t\t\t\t\t\n\t\t\t\t","case_gps_coordinates":"27.05430 -97.793","case_address_found_1":"","case_address_found_2":"","case_city_found":"","case_state_found_id":"Texas","case_zip_found":"","case_county_found_id":"Kenedy","case_circumstances":"Human remains located on 7/12/2016 in Kenedy County, TX.  The only information is that the remains are of a 52-year-old white male, no other description.  It is unknown how this descriptive information was derived. ","case_hair_color":"Unknown or Completely Bald","case_head_hair":"Unknown","case_body_hair":"Unknown","case_facial_hair":"Unknown","case_eye_color_left":"Unknown or Missing","case_eye_color_right":"Unknown or Missing","case_eye_description":"Unknown","case_physical_other_details":"checked","fingerprints":"\n\t\t\t\t\t\n\t\t\t\t\t\tFingerprint information is currently not available\n\t\t\t\t\t\n\t\t\t\t","clothing_accessories":"","case_clothing_on_body":"Unknown","case_clothing_with_body":"Unknown","case_footwear":"Unknown","case_jewelry":"Unknown","case_eyewear":"Unknown","case_other_items_with_body":"Unknown","dental":"\n\t\t\t\t\t\n\t\t\t\t\t\tDental information / charting is currently not available\n\t\t\t\t\t\n\t\t\t\t","dna":"\n\t\t\t\t\t\n\t\t\t\t\t\tSamples submitted - Tests not complete\n\t\t\t\t\t\n\t\t\t\t","images":[],"documents":"\n\t\t\t\t\n\t\t\t\t\tThere are currently no documents available for this case.<br><br><br><br>\n\t\t\t\t\n\t\t\t"}