{"case_report_title":"Case Report - NamUs UP # 407","case_status":"Unidentified","case_number":"06-01285","date_found":"2006-02-11T08:00:00.000Z","date_created":"2007-06-30T07:00:00.000Z","date_last_modified":"2016-06-14T18:44:00.000Z","case_qa_reviewed_date":"2006-02-11T08:00:00.000Z","current_contact":{"agency":"Clark Cnty Coroner Ofc","phone":"702-455-3210"},"case_manager":{"name":"Ashley Grygor","phone":"(702) 455-3210"},"case_estimated_age":"Adult","case_minimum_age":"40 years","case_maximum_age":"55 years","case_race":"White","case_ethnicity":"","case_sex":"Male","case_weight":"\n\t\t\t\t\t,\n\t\t\t\t\tCannot Estimate\n\t\t\t\t","case_height":"\n\t\t\t\t\t67,\n\t\t\t\t\tEstimated\n\t\t\t\t","case_body_inventory_all_parts_recovered":"checked","case_body_condition":"Not recognizable - Decomposing/putrefaction","case_minimum_year_of_death":"\n\t\t\t\t\t2005\n\t\t\t\t\tto\n\t\t\t\t\t2006\n\t\t\t\t","case_postmortem_interval":"\n\t\t\t\t\t6\n\t\t\t\t\tMonths\n\t\t\t\t","case_gps_coordinates":"","case_address_found_1":"I-15 and Russell Rd.","case_address_found_2":"","case_city_found":"","case_state_found_id":"Nevada","case_zip_found":"89113","case_county_found_id":"Clark","case_circumstances":"An employee for NV Dept of Transportation was checking all the wash areas for vagrants or any blockages when he came across the remains of a body in the wash under the on-ramp. The workers have not been in the area for almost a year.","case_hair_color":"Unknown or Completely Bald","case_head_hair":"Wavy brown ","case_body_hair":"N/A","case_facial_hair":"Short brown mustache present extending to the sides of the mouth\nShort brown or possibly silver beard stubble present","case_eye_color_left":"","case_eye_color_right":"","case_eye_description":"","fingerprints":"\n\t\t\t\t\t\n\t\t\t\t\t\tFingerprint information is currently not available\n\t\t\t\t\t\n\t\t\t\t","clothing_accessories":"","case_clothing_on_body":"Gray sweatpants (size ladies M), Tan shorts (Tommy Hilfiger, size 32), Blue/white striped boxers (Izod, size M)","case_clothing_with_body":"N/A","case_footwear":"Black/red tennis shoes (New Balance 704, size 9-1/2 D)","case_jewelry":"N/A","case_eyewear":"N/A","case_other_items_with_body":"","dental":"\n\t\t\t\t\t\n\t\t\t\t\t\tDental information / charting is available and entered\n\t\t\t\t\t\n\t\t\t\t","dna":"\n\t\t\t\t\t\n\t\t\t\t\t\tSample submitted - Tests complete\n\t\t\t\t\t\n\t\t\t\t","images":[],"documents":"\n\t\t\t\t\n\t\t\t\t\tThere are currently no documents available for this case.<br><br><br><br>\n\t\t\t\t\n\t\t\t"}