{"case_report_title":"Case Report - NamUs UP # 643","case_status":"Unidentified","case_number":"81-0151","date_found":"1981-01-19T21:52:00.000Z","date_created":"2007-11-02T20:54:00.000Z","date_last_modified":"2016-08-04T14:06:00.000Z","case_qa_reviewed_date":"1981-01-19T21:52:00.000Z","current_contact":{"agency":"Fulton Cnty Medical Examiners Ofc","phone":"404-613-4400"},"case_manager":{"name":"Tami Sedivy-Schroder","phone":"404.613.4422"},"case_estimated_age":"Adult","case_minimum_age":"18 years","case_maximum_age":"99 years","case_race":"Unsure","case_ethnicity":"","case_sex":"Female","case_weight":"\n\t\t\t\t\t,\n\t\t\t\t\tCannot Estimate\n\t\t\t\t","case_height":"\n\t\t\t\t\t,\n\t\t\t\t\tCannot Estimate\n\t\t\t\t","case_body_inventory_torso_not_recovered":"checked","case_body_inventory_limbs_not_recovered":"checked","case_body_inventory_hands_not_recovered":"checked","case_body_condition":"Not recognizable - Partial remains with soft tissues","case_minimum_year_of_death":"\n\t\t\t\t\t1980\n\t\t\t\t\tto\n\t\t\t\t\t1981\n\t\t\t\t","case_postmortem_interval":"\n\t\t\t\t\t\n\t\t\t\t\tMonths\n\t\t\t\t","case_gps_coordinates":"","case_address_found_1":"4010 Boulderpark SW","case_address_found_2":"","case_city_found":"Atlanta","case_state_found_id":"Georgia","case_zip_found":"","case_county_found_id":"Fulton","case_circumstances":"Skull was found with 6 loose teeth. Possibly brought into yard by a dog. No further infomation is available. ","case_hair_color":"","case_head_hair":"","case_body_hair":"","case_facial_hair":"","case_eye_color_left":"","case_eye_color_right":"","case_eye_description":"","fingerprints":"\n\t\t\t\t\t\n\t\t\t\t\t\tFingerprint information is currently not available\n\t\t\t\t\t\n\t\t\t\t","clothing_accessories":"","case_clothing_on_body":"","case_clothing_with_body":"","case_footwear":"","case_jewelry":"","case_eyewear":"","case_other_items_with_body":"","dental":"\n\t\t\t\t\t\n\t\t\t\t\t\tDental information / charting is currently not available\n\t\t\t\t\t\n\t\t\t\t","dna":"\n\t\t\t\t\t\n\t\t\t\t\t\tSample submitted - Tests complete\n\t\t\t\t\t\n\t\t\t\t","images":["/en/medias/thumb/3232"],"documents":"\n\t\t\t\t\n\t\t\t\t\tThere are currently no documents available for this case.<br><br><br><br>\n\t\t\t\t\n\t\t\t"}