{"case_report_title":"Case Report - NamUs UP # 655","case_status":"Unidentified","case_number":"97-1255","date_found":"1997-08-04T07:00:00.000Z","date_created":"2007-11-05T23:25:00.000Z","date_last_modified":"2016-08-04T14:06:00.000Z","case_qa_reviewed_date":"1997-08-04T07:00:00.000Z","current_contact":{"agency":"Fulton Cnty Medical Examiners Ofc","phone":"404-613-4400"},"case_manager":{"name":"Tami Sedivy-Schroder","phone":"404.613.4422"},"case_estimated_age":"Adult - Pre 50","case_minimum_age":"30 years","case_maximum_age":"50 years","case_race":"White","case_ethnicity":"","case_sex":"Male","case_weight":"\n\t\t\t\t\t197,\n\t\t\t\t\tMeasured\n\t\t\t\t","case_height":"\n\t\t\t\t\t72,\n\t\t\t\t\tMeasured\n\t\t\t\t","case_body_inventory_all_parts_recovered":"checked","case_body_condition":"Recognizable face","case_minimum_year_of_death":"\n\t\t\t\t\t1997\n\t\t\t\t\tto\n\t\t\t\t\t1997\n\t\t\t\t","case_postmortem_interval":"\n\t\t\t\t\t\n\t\t\t\t\tMinutes\n\t\t\t\t","case_gps_coordinates":"","case_address_found_1":"Near Butler Street and Gilmer Street","case_address_found_2":"","case_city_found":"Atlanta ","case_state_found_id":"Georgia","case_zip_found":"30303","case_county_found_id":"Fulton","case_circumstances":"Probably homeless. Had been seen waling in area for a day or two with two suitcases. Collapsed. Taken to hospital where he died. ","case_hair_color":"Black","case_head_hair":"black, 5 inches in length","case_body_hair":"","case_facial_hair":"sideburns","case_eye_color_left":"","case_eye_color_right":"","case_eye_description":"","fingerprints":"\n\t\t\t\t\t\n\t\t\t\t\t\tFingerprint information is available and entered\n\t\t\t\t\t\n\t\t\t\t","clothing_accessories":"","case_clothing_on_body":"","case_clothing_with_body":"","case_footwear":"","case_jewelry":"","case_eyewear":"","case_other_items_with_body":"","dental":"\n\t\t\t\t\t\n\t\t\t\t\t\tDental information / charting is available and entered\n\t\t\t\t\t\n\t\t\t\t","dna":"\n\t\t\t\t\t\n\t\t\t\t\t\tComplete - Insufficient DNA for profiling\n\t\t\t\t\t\n\t\t\t\t","images":["/en/medias/thumb/527"],"documents":"\n\t\t\t\t\n\t\t\t\t\tThere are currently no documents available for this case.<br><br><br><br>\n\t\t\t\t\n\t\t\t"}