{"case_report_title":"Case Report - NamUs UP # 7580","case_status":"Unidentified","case_number":"0235-92","date_found":"1992-02-26T14:23:00.000Z","date_created":"2010-08-14T00:31:00.000Z","date_last_modified":"2011-03-01T18:14:00.000Z","case_qa_reviewed_date":"1992-02-26T14:23:00.000Z","current_contact":{"agency":"Carson City Cnty Coroners Ofc","phone":"775-887-2020"},"case_manager":{"name":"George Gomez","phone":"775-785-6114"},"case_estimated_age":"Adult - Pre 70","case_minimum_age":"60 years","case_maximum_age":"70 years","case_race":"White","case_ethnicity":"","case_sex":"Male","case_weight":"\n\t\t\t\t\t186,\n\t\t\t\t\tMeasured\n\t\t\t\t","case_height":"\n\t\t\t\t\t69,\n\t\t\t\t\tMeasured\n\t\t\t\t","case_body_inventory_all_parts_recovered":"checked","case_body_condition":"Recognizable face","case_minimum_year_of_death":"\n\t\t\t\t\t1992\n\t\t\t\t\tto\n\t\t\t\t\t1992\n\t\t\t\t","case_postmortem_interval":"\n\t\t\t\t\t\n\t\t\t\t\tHours\n\t\t\t\t","case_gps_coordinates":"","case_address_found_1":"813 North Plaza Street","case_address_found_2":"","case_city_found":"Carson City","case_state_found_id":"Nevada","case_zip_found":"","case_county_found_id":"Carson City","case_circumstances":"On 02/26/1992 at 0623 hours, a passerby observed the unresponsive decedent sitting against the east side of the U.S. Geological Survey Department building located in Carson City, Nevada.  There was a .38 caliber Iver Johnson revolver in the decedent's right hand.  The decedent had an intraoral defect with a defect to the top of his head.  A suicide note was not found.","case_hair_color":"","case_head_hair":"Gray, approximately 1\" in length","case_body_hair":"","case_facial_hair":"Beard","case_eye_color_left":"Blue","case_eye_color_right":"Blue","case_eye_description":"","case_amputations_details":"checked","case_scars_and_marks_details":"checked","fingerprints":"\n\t\t\t\t\t\n\t\t\t\t\t\tFingerprint information is available elsewhere\n\t\t\t\t\t\n\t\t\t\t","clothing_accessories":"","case_clothing_on_body":"A dark brown suit, a green sports jacket, a yellow shirt, and a white jumpsuit.","case_clothing_with_body":"","case_footwear":"","case_jewelry":"","case_eyewear":"","case_other_items_with_body":"Two blue pens and a black flashlight.  A .38 caliber Iver Johnson revolver","dental":"\n\t\t\t\t\t\n\t\t\t\t\t\tDental information / charting is available and entered\n\t\t\t\t\t\n\t\t\t\t","dna":"\n\t\t\t\t\t\n\t\t\t\t\t\tSample is currently not available\n\t\t\t\t\t\n\t\t\t\t","images":[],"documents":"\n\t\t\t\t\n\t\t\t\t\tThere are currently no documents available for this case.<br><br><br><br>\n\t\t\t\t\n\t\t\t"}