{"case_report_title":"Case Report - NamUs UP # 8595","case_status":"Unidentified","case_number":"213 July 03","date_found":"2003-07-12T13:00:00.000Z","date_created":"2011-03-25T18:15:00.000Z","date_last_modified":"2015-03-23T22:38:00.000Z","case_qa_reviewed_date":"2003-07-12T13:00:00.000Z","current_contact":{"agency":"Cook Co. Medical Examiner's Office","phone":"312-666-0500"},"case_manager":{"name":"Timothy Doe","phone":"312.997.4494"},"case_estimated_age":"Adult - Pre 50","case_minimum_age":"30 years","case_maximum_age":"40 years","case_race":"White","case_ethnicity":"","case_sex":"Female","case_weight":"\n\t\t\t\t\t147,\n\t\t\t\t\tMeasured\n\t\t\t\t","case_height":"\n\t\t\t\t\t62,\n\t\t\t\t\tMeasured\n\t\t\t\t","case_body_inventory_all_parts_recovered":"checked","case_body_condition":"Recognizable face","case_minimum_year_of_death":"\n\t\t\t\t\t\n\t\t\t\t\tto\n\t\t\t\t\t\n\t\t\t\t","case_postmortem_interval":"\n\t\t\t\t\t\n\t\t\t\t\t\n\t\t\t\t","case_gps_coordinates":"","case_address_found_1":"Chicago River At Willow RD","case_address_found_2":"Cook County Forest Preserve","case_city_found":"","case_state_found_id":"Illinois","case_zip_found":"","case_county_found_id":"Cook","case_circumstances":"Subject was found floating in the Chicago River wrapped in a blanket and bound in duct tape.","case_hair_color":"Black","case_head_hair":"Long & Straight","case_body_hair":"","case_facial_hair":"","case_eye_color_left":"","case_eye_color_right":"","case_eye_description":"","fingerprints":"\n\t\t\t\t\t\n\t\t\t\t\t\tFingerprint information is available and entered\n\t\t\t\t\t\n\t\t\t\t","clothing_accessories":"","case_clothing_on_body":"","case_clothing_with_body":"","case_footwear":"","case_jewelry":"","case_eyewear":"","case_other_items_with_body":"","dental":"\n\t\t\t\t\t\n\t\t\t\t\t\tDental information / charting is available and entered\n\t\t\t\t\t\n\t\t\t\t","dna":"\n\t\t\t\t\t\n\t\t\t\t\t\tComplete - Insufficient DNA for profiling\n\t\t\t\t\t\n\t\t\t\t","images":["/en/medias/thumb/25802","/en/medias/thumb/25803","/en/medias/thumb/25804"],"documents":"\n\t\t\t\t\n\t\t\t\t\tThere are currently no documents available for this case.<br><br><br><br>\n\t\t\t\t\n\t\t\t"}