{"case_report_title":"Case Report - NamUs UP # 8848","case_status":"Unidentified","case_number":"MLA 07-580","date_found":"2007-08-05T07:00:00.000Z","date_created":"2011-06-13T23:35:00.000Z","date_last_modified":"2014-12-16T23:24:00.000Z","case_qa_reviewed_date":"2007-08-05T07:00:00.000Z","current_contact":{"agency":"District 1 Medical Examiners Office","phone":"850-416-7200"},"case_manager":{"name":"Emily Speed","phone":"850-416-7210"},"case_estimated_age":"Adult - Pre 40","case_minimum_age":"25 years","case_maximum_age":"35 years","case_race":"Other","case_ethnicity":"Hispanic/Latino","case_sex":"Male","case_weight":"\n\t\t\t\t\t146,\n\t\t\t\t\tMeasured\n\t\t\t\t","case_height":"\n\t\t\t\t\t67,\n\t\t\t\t\tMeasured\n\t\t\t\t","case_body_inventory_all_parts_recovered":"checked","case_body_condition":"Recognizable face","case_minimum_year_of_death":"\n\t\t\t\t\t2007\n\t\t\t\t\tto\n\t\t\t\t\t2007\n\t\t\t\t","case_postmortem_interval":"\n\t\t\t\t\t\n\t\t\t\t\t\n\t\t\t\t","case_gps_coordinates":"","case_address_found_1":"State Road 189 ","case_address_found_2":"Manring Drive","case_city_found":"Ft. Walton Beach","case_state_found_id":"Florida","case_zip_found":"","case_county_found_id":"Okaloosa","case_circumstances":"Decedent was a pedestrian involved in a motor vehicle accident.  The decedent reportedly went by the name \"Antonio Escobar\", however, no identification, NOK, or antemortem records are available at this time for confirmation.","case_hair_color":"Black","case_head_hair":"","case_body_hair":"","case_facial_hair":"Moustache and goatee present","case_eye_color_left":"Brown","case_eye_color_right":"Brown","case_eye_description":"","case_physical_other_details":"checked","fingerprints":"\n\t\t\t\t\t\n\t\t\t\t\t\tFingerprint information is available and entered\n\t\t\t\t\t\n\t\t\t\t","clothing_accessories":"","case_clothing_on_body":"Polo style shirt, khaki shorts, khaki belt, gray boxer briefs","case_clothing_with_body":"","case_footwear":"Two black and white tennis shoes","case_jewelry":"Yellow metal chain","case_eyewear":"","case_other_items_with_body":"White cap","dental":"\n\t\t\t\t\t\n\t\t\t\t\t\tDental information / charting is currently not available\n\t\t\t\t\t\n\t\t\t\t","dna":"\n\t\t\t\t\t\n\t\t\t\t\t\tSample is currently not available\n\t\t\t\t\t\n\t\t\t\t","images":[],"documents":"\n\t\t\t\t\n\t\t\t\t\tThere are currently no documents available for this case.<br><br><br><br>\n\t\t\t\t\n\t\t\t"}