{"case_report_title":"Case Report - NamUs UP # 9926","case_status":"Unidentified","case_number":"75-34, 80-13306","date_found":"1975-01-22T17:00:00.000Z","date_created":"2012-02-27T20:53:00.000Z","date_last_modified":"2016-03-28T17:38:00.000Z","case_qa_reviewed_date":"1975-01-22T17:00:00.000Z","current_contact":{"agency":"Clackamas County ME’s Office","phone":"971-673-8300"},"case_manager":{"name":"Veronica Vance","phone":"971.673.8300"},"case_estimated_age":"Adult - Pre 50","case_minimum_age":"18 years","case_maximum_age":"50 years","case_race":"Unsure","case_ethnicity":"","case_sex":"Male","case_weight":"\n\t\t\t\t\t,\n\t\t\t\t\tCannot Estimate\n\t\t\t\t","case_height":"\n\t\t\t\t\t,\n\t\t\t\t\tCannot Estimate\n\t\t\t\t","case_body_condition":"Not recognizable - Partial skeletal parts only","case_minimum_year_of_death":"\n\t\t\t\t\t\n\t\t\t\t\tto\n\t\t\t\t\t\n\t\t\t\t","case_postmortem_interval":"\n\t\t\t\t\t\n\t\t\t\t\tYears\n\t\t\t\t","case_gps_coordinates":"","case_address_found_1":"Mt. Hood National Forest","case_address_found_2":"Near Service Rd S-57G, ","case_city_found":"4.5 mi SE of Ripplebrook Ranger Station","case_state_found_id":"Oregon","case_zip_found":"","case_county_found_id":"Clackamas","case_circumstances":"On two separate occasions, partial human remains were discovered  in 1975 and again in 1980, above Ripplebrook in Clackamas County and off of  Forest Service Road S-57G. The location was then searched and additional teeth and possible human bone fragments were discovered.  These two cases were associated by DNA in 2012.  UP 7460 and UP9926 have been identified as being the same individual.  This is a probable homicide victim, and this location may have been a dump site.","case_hair_color":"","case_head_hair":"","case_body_hair":"","case_facial_hair":"","case_eye_color_left":"","case_eye_color_right":"","case_eye_description":"","fingerprints":"\n\t\t\t\t\t\n\t\t\t\t\t\tFingerprint information is currently not available\n\t\t\t\t\t\n\t\t\t\t","clothing_accessories":"","case_clothing_on_body":"","case_clothing_with_body":"Trousers, light brown checkered pattern\nBlack leather belt","case_footwear":"","case_jewelry":"","case_eyewear":"","case_other_items_with_body":"Brown button","dental":"\n\t\t\t\t\t\n\t\t\t\t\t\tDental information / charting is available and entered\n\t\t\t\t\t\n\t\t\t\t","dna":"\n\t\t\t\t\t\n\t\t\t\t\t\tSample submitted - Tests complete\n\t\t\t\t\t\n\t\t\t\t","images":["/en/medias/thumb/12858","/en/medias/thumb/13330"],"documents":"\n\t\t\t\t\n\t\t\t\t\tThere are currently no documents available for this case.<br><br><br><br>\n\t\t\t\t\n\t\t\t"}